igym/__init__.py
igym/core.py
inno_gym-0.0.1.dist-info/licenses/LICENSE
inno_gym-0.0.1.dist-info/METADATA
inno_gym-0.0.1.dist-info/WHEEL
inno_gym-0.0.1.dist-info/top_level.txt
inno_gym-0.0.1.dist-info/RECORD
